brother/__init__.py
brother/const.py
brother/exceptions.py
brother/model.py
brother/py.typed
brother/utils.py
brother-5.1.1.dist-info/licenses/LICENSE
brother-5.1.1.dist-info/METADATA
brother-5.1.1.dist-info/WHEEL
brother-5.1.1.dist-info/top_level.txt
brother-5.1.1.dist-info/RECORD
