Metadata-Version: 2.4
Name: brother
Version: 5.1.1
Summary: Python wrapper for getting data from Brother laser and inkjet printers via SNMP.
Author: Maciej Bieniek
License-Expression: Apache-2.0
Project-URL: Homepage, https://github.com/bieniu/brother
Classifier: Development Status :: 5 - Production/Stable
Classifier: Operating System :: OS Independent
Classifier: Programming Language :: Python
Classifier: Programming Language :: Python :: 3
Classifier: Programming Language :: Python :: 3.12
Classifier: Programming Language :: Python :: 3.13
Classifier: Programming Language :: Python :: 3 :: Only
Classifier: Typing :: Typed
Requires-Python: >=3.12
License-File: LICENSE
Requires-Dist: dacite>=1.7.0
Requires-Dist: pysnmp>=7.1.6
Provides-Extra: test
Requires-Dist: coverage==7.10.7; extra == "test"
Requires-Dist: freezegun==1.5.5; extra == "test"
Requires-Dist: mypy==1.18.2; extra == "test"
Requires-Dist: pytest-asyncio==1.2.0; extra == "test"
Requires-Dist: pytest-cov==7.0.0; extra == "test"
Requires-Dist: pytest-error-for-skips==2.0.2; extra == "test"
Requires-Dist: pytest-timeout==2.4.0; extra == "test"
Requires-Dist: pytest==8.4.2; extra == "test"
Requires-Dist: ruff==0.13.3; extra == "test"
Requires-Dist: syrupy==5.0.0; extra == "test"
Provides-Extra: dev
Requires-Dist: pre-commit==4.3.0; extra == "dev"
Dynamic: license-file
